django_zooy/__init__.py
django_zooy/base.py
django_zooy/carbon/__init__.py
django_zooy/carbon/icons.py
django_zooy/carbon/mixins.py
django_zooy/carbon/widgets/__init__.py
django_zooy/carbon/widgets/base.py
django_zooy/carbon/widgets/checkbox.py
django_zooy/carbon/widgets/date_picker.py
django_zooy/carbon/widgets/dropdown.py
django_zooy/carbon/widgets/radio.py
django_zooy/carbon/widgets/text_input.py
django_zooy/carbon/widgets/textarea_input.py
django_zooy/management/__init__.py
django_zooy/management/commands/__init__.py
django_zooy/management/commands/fetch_carbon_assets.py
django_zooy/mdc/__init__.py
django_zooy/py.typed
django_zooy/templates/django_zooy/carbon/data_table_batch_filter.html
django_zooy/templates/django_zooy/carbon/modal.html
django_zooy/templates/django_zooy/carbon/modal_form.html
django_zooy/templates/django_zooy/carbon/widgets/checkbox.html
django_zooy/templates/django_zooy/carbon/widgets/checkbox_option.html
django_zooy/templates/django_zooy/carbon/widgets/checkbox_select_multiple.html
django_zooy/templates/django_zooy/carbon/widgets/date_picker.html
django_zooy/templates/django_zooy/carbon/widgets/dropdown.html
django_zooy/templates/django_zooy/carbon/widgets/password_input.html
django_zooy/templates/django_zooy/carbon/widgets/radio_option.html
django_zooy/templates/django_zooy/carbon/widgets/radio_select.html
django_zooy/templates/django_zooy/carbon/widgets/text_input.html
django_zooy/templates/django_zooy/carbon/widgets/textarea.html
django_zooy/templatetags/__init__.py
django_zooy/templatetags/carbon.py
django_zooy/templatetags/zooy.py
django_zooy/utils.py
django_zooy-0.2.11.dist-info/WHEEL
django_zooy-0.2.11.dist-info/METADATA
django_zooy-0.2.11.dist-info/RECORD
