Metadata-Version: 2.3
Name: django-zooy
Version: 0.2.11
Summary: Django integration for Zooy UI framework with Carbon Design System widgets
Author: Jan Badenhorst
Author-email: Jan Badenhorst <jan@trintel.co.za>
License: MIT
Classifier: Framework :: Django
Classifier: Framework :: Django :: 5.0
Classifier: Programming Language :: Python :: 3
Classifier: Programming Language :: Python :: 3.11
Classifier: Programming Language :: Python :: 3.12
Classifier: License :: OSI Approved :: MIT License
Classifier: Operating System :: OS Independent
Classifier: Intended Audience :: Developers
Classifier: Topic :: Software Development :: Libraries :: Python Modules
Classifier: Topic :: Software Development :: User Interfaces
Requires-Dist: django>=3.2
Requires-Dist: pytest>=8.0.0 ; extra == 'dev'
Requires-Dist: pytest-django>=4.5.0 ; extra == 'dev'
Requires-Dist: ruff>=0.12.3 ; extra == 'dev'
Requires-Dist: uv-build ; extra == 'dev'
Requires-Python: >=3.11
Project-URL: Documentation, https://github.com/trinity-telecomms/django-zooy#readme
Project-URL: Homepage, https://github.com/trinity-telecomms/django-zooy
Project-URL: Issues, https://github.com/trinity-telecomms/django-zooy/issues
Project-URL: Repository, https://github.com/trinity-telecomms/django-zooy
Provides-Extra: all
Provides-Extra: carbon
Provides-Extra: dev
Provides-Extra: mdc
